CHANGES.txt
LICENSE.txt
MANIFEST.in
README.rst
setup.py
js/__init__.py
js.bootstrap.egg-info/PKG-INFO
js.bootstrap.egg-info/SOURCES.txt
js.bootstrap.egg-info/dependency_links.txt
js.bootstrap.egg-info/entry_points.txt
js.bootstrap.egg-info/namespace_packages.txt
js.bootstrap.egg-info/not-zip-safe
js.bootstrap.egg-info/requires.txt
js.bootstrap.egg-info/top_level.txt
js/bootstrap/__init__.py
js/bootstrap/test_bootstrap.txt
js/bootstrap/resources/css/bootstrap-theme.css
js/bootstrap/resources/css/bootstrap-theme.css.map
js/bootstrap/resources/css/bootstrap-theme.min.css
js/bootstrap/resources/css/bootstrap.css
js/bootstrap/resources/css/bootstrap.css.map
js/bootstrap/resources/css/bootstrap.min.css
js/bootstrap/resources/fonts/glyphicons-halflings-regular.eot
js/bootstrap/resources/fonts/glyphicons-halflings-regular.svg
js/bootstrap/resources/fonts/glyphicons-halflings-regular.ttf
js/bootstrap/resources/fonts/glyphicons-halflings-regular.woff
js/bootstrap/resources/js/bootstrap.js
js/bootstrap/resources/js/bootstrap.min.js