Metadata-Version: 1.0
Name: js.bootstrap
Version: 3.3.1
Summary: fanstatic twitter bootstrap.
Home-page: https://github.com/RedTurtle/js.bootstrap
Author: RedTurtle Developers
Author-email: sviluppoplone@redturtle.it
License: BSD
Keywords: fanstatic twitter bootstrap redturtle
Platform: UNKNOWN
